dPCA/__init__.py
dPCA/dPCA.py
dPCA/utils.py
dPCA-1.0.5.dist-info/METADATA
dPCA-1.0.5.dist-info/WHEEL
dPCA-1.0.5.dist-info/top_level.txt
dPCA-1.0.5.dist-info/RECORD
