Metadata-Version: 2.1
Name: dPCA
Version: 1.0.5
Summary: Implements Demixed Principal Components Analysis
Home-page: https://github.com/machenslab/dPCA/
Author: Machens Lab
Author-email: wieland.brendel@uni-tuebingen.de
Maintainer: Wieland Brendel
Maintainer-email: wieland.brendel@uni-tuebingen.de
License: MIT
Download-URL: https://github.com/machenslab/dPCA/
Platform: UNKNOWN
Requires: sklearn
Requires: numexpr
Requires: numba
